onbrdng
