Metadata-Version: 2.1
Name: onbrdng
Version: 0.0.2
Summary: Package that makes it a bit easier to understand some complex models and helps you visualize them
Home-page: UNKNOWN
Author: Data modelling team Onbrdng
Author-email: can.yildiz@onbrdng.com
License: MIT
Platform: UNKNOWN
Classifier: Programming Language :: Python :: 3
Classifier: License :: OSI Approved :: MIT License
Classifier: Operating System :: OS Independent
